turinium/__init__.py
turinium/config/__init__.py
turinium/config/app_config.py
turinium/config/shared_app_config.py
turinium/database/__init__.py
turinium/database/db_connection.py
turinium/database/db_credentials.py
turinium/database/db_router.py
turinium/database/db_services.py
turinium/datasources/__init__.py
turinium/datasources/base.py
turinium/datasources/data_source_services.py
turinium/datasources/ftp.py
turinium/datasources/ftp_connection.py
turinium/datasources/ftp_credentials.py
turinium/email/__init__.py
turinium/email/email.py
turinium/logging/__init__.py
turinium/logging/logging.py
turinium-0.2.2.dist-info/METADATA
turinium-0.2.2.dist-info/WHEEL
turinium-0.2.2.dist-info/top_level.txt
turinium-0.2.2.dist-info/RECORD
