Metadata-Version: 2.4
Name: turinium
Version: 0.2.2
Summary: Turinium is a Python framework designed to streamline software development by reducing boilerplate code and providing utility functions for database connections, logging, error handling, and configuration management.
Author-email: Milton Lapido <milton.lapido@gmail.com>
License: MIT
Keywords: software development,utilities,database,logging,configuration,python framework
Classifier: Development Status :: 3 - Alpha
Classifier: Intended Audience :: Developers
Classifier: License :: OSI Approved :: MIT License
Classifier: Programming Language :: Python :: 3
Classifier: Programming Language :: Python :: 3.8
Classifier: Programming Language :: Python :: 3.9
Classifier: Programming Language :: Python :: 3.10
Classifier: Programming Language :: Python :: 3.11
Classifier: Programming Language :: Python :: 3.12
Classifier: Programming Language :: Python :: 3.13
Classifier: Topic :: Software Development :: Libraries :: Python Modules
Requires-Python: >=3.8
Requires-Dist: pyyaml
Requires-Dist: toml
Requires-Dist: json5
Requires-Dist: python-dotenv
Requires-Dist: colorlog
Requires-Dist: sqlalchemy
Requires-Dist: paramiko
Provides-Extra: database-odbc
Requires-Dist: sqlalchemy; extra == "database-odbc"
Requires-Dist: pyodbc; extra == "database-odbc"
Requires-Dist: difflib; extra == "database-odbc"
Requires-Dist: pandas; extra == "database-odbc"
Provides-Extra: database-pg
Requires-Dist: sqlalchemy; extra == "database-pg"
Requires-Dist: psycopg2-binary; extra == "database-pg"
Requires-Dist: pandas; extra == "database-pg"
Provides-Extra: database-all
Requires-Dist: sqlalchemy; extra == "database-all"
Requires-Dist: pyodbc; extra == "database-all"
Requires-Dist: psycopg2-binary; extra == "database-all"
Requires-Dist: difflib; extra == "database-all"
Requires-Dist: pandas; extra == "database-all"
Provides-Extra: cli
Requires-Dist: click; extra == "cli"
Provides-Extra: testing
Requires-Dist: pytest; extra == "testing"
Requires-Dist: pytest-cov; extra == "testing"
Provides-Extra: dev
Requires-Dist: black; extra == "dev"
Requires-Dist: flake8; extra == "dev"
Requires-Dist: mypy; extra == "dev"
Provides-Extra: docs
Requires-Dist: mkdocs; extra == "docs"
Requires-Dist: mkdocs-material; extra == "docs"
Requires-Dist: mkdocstrings[python]; extra == "docs"
Requires-Dist: mkdocs-awesome-pages-plugin; extra == "docs"
Requires-Dist: mkdocs-git-revision-date-localized-plugin; extra == "docs"
Requires-Dist: mike; extra == "docs"
